amnemone/__about__.py
amnemone/__init__.py
amnemone/__main__.py
amnemone/abc.py
amnemone/models.py
amnemone/data/__init__.py
amnemone/data/bip39/__init__.py
amnemone/data/bip39/chinese_simplified.txt
amnemone/data/bip39/chinese_traditional.txt
amnemone/data/bip39/czech.txt
amnemone/data/bip39/english.txt
amnemone/data/bip39/french.txt
amnemone/data/bip39/italian.txt
amnemone/data/bip39/japanese.txt
amnemone/data/bip39/korean.txt
amnemone/data/bip39/portuguese.txt
amnemone/data/bip39/russian.txt
amnemone/data/bip39/spanish.txt
amnemone/data/bip39/turkish.txt
amnemone/data/countries_states_cities/__init__.py
amnemone/data/countries_states_cities/cities.csv
amnemone/data/countries_states_cities/countries.csv
amnemone/data/countries_states_cities/regions.csv
amnemone/data/countries_states_cities/states.csv
amnemone/data/countries_states_cities/subregions.csv
amnemone/data/words/__init__.py
amnemone/data/words/an-array-of-english-words.json
amnemone-0.2.0.dist-info/METADATA
amnemone-0.2.0.dist-info/WHEEL
amnemone-0.2.0.dist-info/licenses/LICENSE.txt
amnemone-0.2.0.dist-info/RECORD
