Metadata-Version: 2.3
Name: amnemone
Version: 0.2.0
Project-URL: Documentation, https://github.com/danlsn/amnemone#readme
Project-URL: Issues, https://github.com/danlsn/amnemone/issues
Project-URL: Source, https://github.com/danlsn/amnemone
Author-email: Daniel Lawson <52593003+danlsn@users.noreply.github.com>
License-Expression: MIT
License-File: LICENSE.txt
Classifier: Development Status :: 4 - Beta
Classifier: Programming Language :: Python
Classifier: Programming Language :: Python :: 3.8
Classifier: Programming Language :: Python :: 3.9
Classifier: Programming Language :: Python :: 3.10
Classifier: Programming Language :: Python :: 3.11
Classifier: Programming Language :: Python :: 3.12
Classifier: Programming Language :: Python :: Implementation :: CPython
Requires-Python: >=3.8
Requires-Dist: bidict>=0.23.1
